discot/__init__.py
discot/discot.py
discot-1.0.4.dist-info/LICENSE
discot-1.0.4.dist-info/METADATA
discot-1.0.4.dist-info/WHEEL
discot-1.0.4.dist-info/top_level.txt
discot-1.0.4.dist-info/RECORD
