Metadata-Version: 2.1
Name: discot
Version: 1.0.4
Summary: Discord bot creation framework
Home-page: https://github.com/qbius/discot
Author: Michał Surówka
Author-email: michalpiotrsurowka@gmail.com
License: UNKNOWN
Platform: UNKNOWN
Classifier: Programming Language :: Python :: 3
Classifier: License :: OSI Approved :: MIT License
Classifier: Operating System :: OS Independent
License-File: LICENSE
Requires-Dist: disnake
